librivox/__init__.py
librivox/entities.py
librivox/librivox.py
librivox/py.typed
librivox/typing.py
librivox-0.1.dist-info/METADATA
librivox-0.1.dist-info/WHEEL
librivox-0.1.dist-info/licenses/LICENSES/AGPL-3.0-or-later.md
librivox-0.1.dist-info/licenses/LICENSES/CC0-1.0.txt
librivox-0.1.dist-info/RECORD
